pseudoku/Generator.py
pseudoku/Solver.py
pseudoku/__init__.py
pseudoku-0.0.1.dist-info/LICENSE
pseudoku-0.0.1.dist-info/METADATA
pseudoku-0.0.1.dist-info/WHEEL
pseudoku-0.0.1.dist-info/top_level.txt
pseudoku-0.0.1.dist-info/RECORD
