Metadata-Version: 2.1
Name: pseudoku
Version: 0.0.1
Summary: A Sudoku puzzle solver and generator
Author-email: Joe Gretton <joegretton96@gmail.com>
Project-URL: Homepage, https://github.com/Grettz/Pseudoku
Project-URL: Issues, https://github.com/Grettz/Pseudoku/issues
Keywords: sudoku,sudoku solver,sudoku generator
Classifier: Programming Language :: Python :: 3
Classifier: License :: OSI Approved :: MIT License
Classifier: Operating System :: OS Independent
Requires-Python: >=3.8
License-File: LICENSE
